HugSqlTools/__init__.py
HugSqlTools/tag_template_constants.py
HugSqlTools/tag_template_manager.py
HugSqlTools/test_unit.py
HugSqlTools/tag_template_engine/__init__.py
HugSqlTools/tag_template_engine/ads_engine/__init__.py
HugSqlTools/tag_template_engine/ads_engine/ads_config.py
HugSqlTools/tag_template_engine/ads_engine/ads_manager.py
HugSqlTools/tag_template_engine/config_engine/__init__.py
HugSqlTools/tag_template_engine/config_engine/config_manager.py
HugSqlTools/tag_template_engine/constants_engine/__init__.py
HugSqlTools/tag_template_engine/constants_engine/constants.py
HugSqlTools/tag_template_engine/input_engine/__init__.py
HugSqlTools/tag_template_engine/input_engine/input_manager.py
HugSqlTools/tag_template_engine/input_engine/input_tip_constants.py
HugSqlTools/tag_template_engine/service_engine/__init__.py
HugSqlTools/tag_template_engine/service_engine/service_manager.py
HugSqlTools/tag_template_engine/template_engine/__init__.py
HugSqlTools/tag_template_engine/template_engine/template_config.py
HugSqlTools/tag_template_engine/template_engine/template_manager.py
HugSqlTools/tag_template_engine/template_engine/tag_templates/__init__.py
HugSqlTools/tag_template_engine/utils_engine/__init__.py
HugSqlTools/tag_template_engine/utils_engine/core_utils.py
HugSqlTools/tag_template_engine/utils_engine/git_utils.py
HugSqlProj-1.0.0.dist-info/LICENSE
HugSqlProj-1.0.0.dist-info/METADATA
HugSqlProj-1.0.0.dist-info/WHEEL
HugSqlProj-1.0.0.dist-info/top_level.txt
HugSqlProj-1.0.0.dist-info/RECORD
